uphy/device/__init__.py
uphy/device/__main__.py
uphy/device/api.cpython-310-x86_64-linux-gnu.so
uphy/device/handler.py
uphy/device/api/__init__.cpp
uphy/device/api/__init__.pxd
uphy/device/api/__init__.pyi
uphy/device/api/__init__.pyx
uphy/device/gui/__init__.py
uphy/device/gui/dear.py
uphy/device/gui/rich.py
uphy/device/server/__init__.py
uphy/device/server/bin/server
uphy/device/share/digio.json
uphy/device/share/set_network_parameters
uphy/device/share/set_profinet_leds
uphy_device-1.0.3.dist-info/METADATA
uphy_device-1.0.3.dist-info/WHEEL
uphy_device-1.0.3.dist-info/entry_points.txt
uphy_device-1.0.3.dist-info/top_level.txt
uphy_device-1.0.3.dist-info/RECORD
uphy_device-1.0.3.dist-info/licenses/LICENSE.txt
