Metadata-Version: 2.4
Name: uphy-device
Version: 1.0.3
Author-email: RT-Labs <support@rt-labs.com>
License-Expression: LicenseRef-RT-Labs-Commercial-Agreement
Project-URL: RT-Labs, https://rt-labs.com
Project-URL: U-Phy, https://rt-labs.com/u-phy
Project-URL: Documentation, https://docs.rt-labs.com/u-phy
Requires-Python: >=3.10
License-File: LICENSE.txt
Requires-Dist: yarl>=1.15.2
Requires-Dist: typer>=0.12.5
Requires-Dist: rich>=13.9.2
Requires-Dist: dearpygui>=2.0.0
Requires-Dist: uphy-upgen>=1.0.3
Requires-Dist: yarl>=1.12.1
Requires-Dist: uphy
Requires-Dist: ifaddr>=0.2.0
Dynamic: license-file
